LICENSE
README.md
setup.py
tests/test_unit_arithmetics.py
tests/test_unit_comparing.py
tests/test_unit_conversion.py
tests/test_unit_creation.py
tests/test_unit_dto.py
tests/test_unit_formatting.py
unitsnet_py/__init__.py
unitsnet_py/abstract_unit.py
unitsnet_py.egg-info/PKG-INFO
unitsnet_py.egg-info/SOURCES.txt
unitsnet_py.egg-info/dependency_links.txt
unitsnet_py.egg-info/top_level.txt
unitsnet_py/units/absorbed_dose_of_ionizing_radiation.py
unitsnet_py/units/acceleration.py
unitsnet_py/units/amount_of_substance.py
unitsnet_py/units/amplitude_ratio.py
unitsnet_py/units/angle.py
unitsnet_py/units/area.py
unitsnet_py/units/area_density.py
unitsnet_py/units/area_moment_of_inertia.py
unitsnet_py/units/bit_rate.py
unitsnet_py/units/brake_specific_fuel_consumption.py
unitsnet_py/units/coefficient_of_thermal_expansion.py
unitsnet_py/units/compressibility.py
unitsnet_py/units/density.py
unitsnet_py/units/dose_area_product.py
unitsnet_py/units/duration.py
unitsnet_py/units/dynamic_viscosity.py
unitsnet_py/units/electric_admittance.py
unitsnet_py/units/electric_apparent_energy.py
unitsnet_py/units/electric_apparent_power.py
unitsnet_py/units/electric_capacitance.py
unitsnet_py/units/electric_charge.py
unitsnet_py/units/electric_charge_density.py
unitsnet_py/units/electric_conductance.py
unitsnet_py/units/electric_conductivity.py
unitsnet_py/units/electric_current.py
unitsnet_py/units/electric_current_density.py
unitsnet_py/units/electric_current_gradient.py
unitsnet_py/units/electric_field.py
unitsnet_py/units/electric_impedance.py
unitsnet_py/units/electric_inductance.py
unitsnet_py/units/electric_potential.py
unitsnet_py/units/electric_potential_change_rate.py
unitsnet_py/units/electric_reactance.py
unitsnet_py/units/electric_reactive_energy.py
unitsnet_py/units/electric_reactive_power.py
unitsnet_py/units/electric_resistance.py
unitsnet_py/units/electric_resistivity.py
unitsnet_py/units/electric_surface_charge_density.py
unitsnet_py/units/electric_susceptance.py
unitsnet_py/units/energy.py
unitsnet_py/units/energy_density.py
unitsnet_py/units/entropy.py
unitsnet_py/units/fluid_resistance.py
