Metadata-Version: 2.4
Name: unitsnet-py
Version: 1.0.5
Summary: A better way to hold unit variables and easily convert to the destination unit
Home-page: https://github.com/haimkastner/unitsnet-py
Author: Haim Kastner
Author-email: hello@haim-kastner.com
Maintainer: Haim Kastner
Maintainer-email: hello@haim-kastner.com
License: MIT
Project-URL: Source, https://github.com/haimkastner/unitsnet-py
Project-URL: Documentation, https://github.com/haimkastner/unitsnet-py#readme
Project-URL: Issue Tracker, https://github.com/haimkastner/unitsnet-py/issues
Keywords: conversion,units-of-measure,units,quantities,unit-converter,converter,unit,measure,measures,measurement,measurements
Classifier: License :: OSI Approved :: MIT License
Classifier: Programming Language :: Python :: 3
Classifier: Programming Language :: Python :: 3.8
Classifier: Programming Language :: Python :: 3.9
Classifier: Programming Language :: Python :: 3.10
Classifier: Programming Language :: Python :: 3.11
Classifier: Intended Audience :: Developers
Classifier: Topic :: Software Development :: Libraries :: Python Modules
Requires-Python: >=3.8,<4.0
License-File: LICENSE
Dynamic: author
Dynamic: author-email
Dynamic: classifier
Dynamic: description
Dynamic: description-content-type
Dynamic: home-page
Dynamic: keywords
Dynamic: license
Dynamic: license-file
Dynamic: maintainer
Dynamic: maintainer-email
Dynamic: project-url
Dynamic: requires-python
Dynamic: summary
